.coveragerc
.gitattributes
.gitignore
.style.yapf
CHANGELOG.md
CONTRIBUTING.md
Dockerfile
Dockerfile-jupyterlab
LICENSE
MANIFEST.in
README.md
circle.yml
conda-requirements-test.sh
environment.yml
nglview-js-widgets.json
nglview.png
nightwatch.json
pip-requirements-test.txt
pyproject.toml
run_tests.sh
setup.py
talks.md
.github/ISSUE_TEMPLATE.md
.github/nglview-gha.yml
.github/workflows/build-extension.yml
.github/workflows/test.yml
devtools/README.release
devtools/build_docker.sh
devtools/create_labextension_symlink.py
devtools/gifipy.py
devtools/make_test_js.py
devtools/nglview-jupyterlab.sh
devtools/release.py
devtools/update_versions.py
devtools/circleci/install_miniconda.sh
devtools/conda-recipe/build.sh
devtools/conda-recipe/meta.yaml
devtools/nb_runner/start_server.sh
devtools/nb_runner/stop_server.sh
devtools/outdated/nglview-jupyterlab.sh
devtools/recipe/build.sh
devtools/recipe/meta.yaml
devtools/recipe/post-link.sh
docs/FAQ.md
docs/Makefile
docs/README.md
docs/api.rst
docs/big.pdb
docs/changelog.rst
docs/conf.py
docs/contributing.rst
docs/embed.md
docs/index.md
docs/index.rst
docs/interface_classes.md
docs/interface_classes.rst
docs/make.bat
docs/md_1u19.txt
docs/ngl.js
docs/ngl_player.html
docs/nglview.png
docs/scripts.rst
docs/talks.rst
docs/two_windows.rst
docs/view_demo.html
docs/_api/modules.rst
docs/_api/nglview.adaptor.rst
docs/_api/nglview.contrib.movie.rst
docs/_api/nglview.datafiles.rst
docs/_api/nglview.jsutils.rst
docs/_api/nglview.layout.rst
docs/_api/nglview.player.rst
docs/_api/nglview.scripts.rst
docs/_api/nglview.shape.rst
docs/_api/nglview.static.rst
docs/_api/nglview.theme.rst
docs/_api/nglview.widget.rst
docs/_api/nglview.widget_utils.rst
docs/_static/cindex.js
docs/images/nglview_2windows.png
docs/nglview-jupyterlab/environment.yml
docs/nglview-jupyterlab/index.md
examples/README.md
examples/customize_color.md
examples/jupyterlab.md
examples/mdanalysis.md
examples/mdtraj.md
examples/parmed.md
examples/parmed_minimization.md
nglview.egg-info/PKG-INFO
nglview.egg-info/SOURCES.txt
nglview.egg-info/dependency_links.txt
nglview.egg-info/not-zip-safe
nglview.egg-info/requires.txt
nglview.egg-info/top_level.txt
